impactpy/__init__.py
impactpy/alpha/__init__.py
impactpy/alpha/alpha.py
impactpy/book/__init__.py
impactpy/book/book.py
impactpy/data/__init__.py
impactpy/data/bin_schedule.py
impactpy/data/market_data.py
impactpy/data/schema.py
impactpy/error/__init__.py
impactpy/error/error.py
impactpy/model/__init__.py
impactpy/model/model.py
impactpy/model/model_mk2.py
impactpy/model/subroutines.py
impactpy/model/transformers.py
impactpy/order/__init__.py
impactpy/order/order.py
impactpy/tca/__init__.py
impactpy/tca/tca.py
impactpy-0.0.19.dist-info/METADATA
impactpy-0.0.19.dist-info/WHEEL
impactpy-0.0.19.dist-info/RECORD
